eglRenderer.cpython-39-x86_64-linux-gnu.so
pycram_bullet.cpython-39-x86_64-linux-gnu.so
pybullet_examples/vhacd.py
pybullet_examples/satCollision.py
pybullet_examples/deformable_torus.py
pybullet_examples/inverse_kinematics_pole.py
pybullet_examples/signedDistanceField.py
pybullet_examples/inverse_dynamics.py
pybullet_examples/inverse_kinematics_husky_kuka.py
pybullet_examples/profileTiming.py
pybullet_examples/constraint.py
pybullet_examples/transparent.py
pybullet_examples/testrender_np.py
pybullet_examples/createMultiBodyBatch.py
pybullet_examples/inverse_kinematics.py
pybullet_examples/sceneAabb.py
pybullet_examples/testrender_egl.py
pybullet_examples/experimentalCcdSphereRadius.py
pybullet_examples/pdControllerStable.py
pybullet_examples/fileIOPlugin.py
pybullet_examples/createObstacleCourse.py
pybullet_examples/humanoidMotionCapture.py
pybullet_examples/getTextureUid.py
pybullet_examples/getClosestPoints.py
pybullet_examples/__init__.py
pybullet_examples/projective_texture.py
pybullet_examples/snake.py
pybullet_examples/vr_kuka_setup.py
pybullet_examples/heightfield.py
pybullet_examples/soccerball.py
pybullet_examples/mimicJointConstraint.py
pybullet_examples/manyspheres.py
pybullet_examples/biped2d_pybullet.py
pybullet_examples/pdControllerExplicit.py
pybullet_examples/motorMaxVelocity.py
pybullet_examples/pointCloudFromCameraImage.py
pybullet_examples/sleeptest.py
pybullet_examples/jacobian.py
pybullet_examples/rollPitchYaw.py
pybullet_examples/deformable_anchor.py
pybullet_examples/video_sync_mp4.py
pybullet_examples/switchConstraintSolver.py
pybullet_examples/pdControl.py
pybullet_examples/collisionFilter.py
pybullet_examples/createVisualShapeArray.py
pybullet_envs/scene_abstract.py
pybullet_envs/env_bases.py
pybullet_envs/kerasrl_utils.py
pybullet_envs/scene_stadium.py
pybullet_envs/gym_locomotion_envs.py
pybullet_envs/robot_bases.py
pybullet_envs/robot_locomotors.py
pybullet_envs/__init__.py
pycram_bullet-3.2.8.dist-info/METADATA
pycram_bullet-3.2.8.dist-info/top_level.txt
pycram_bullet-3.2.8.dist-info/RECORD
pycram_bullet-3.2.8.dist-info/WHEEL
pycram_bullet-3.2.8.dist-info/AUTHORS.txt
pycram_bullet-3.2.8.dist-info/LICENSE.txt
