Metadata-Version: 2.1
Name: pycram_bullet
Version: 3.2.8
Summary: Official Python Interface for the Bullet Physics SDK specialized for Robotics Simulation and Reinforcement Learning
Home-page: https://github.com/cram2/bullet3
Author: Jonas Dech
Author-email: pycram@informatik.uni-bremen.de
License: zlib
Keywords: game development,virtual reality,physics simulation,robotics,collision detection,opengl
Platform: any
Classifier: Development Status :: 5 - Production/Stable
Classifier: License :: OSI Approved :: zlib/libpng License
Classifier: Operating System :: Microsoft :: Windows
Classifier: Operating System :: POSIX :: Linux
Classifier: Operating System :: MacOS
Classifier: Intended Audience :: Science/Research
Classifier: Programming Language :: Python
Classifier: Programming Language :: Python :: 2.7
Classifier: Programming Language :: Python :: 3.4
Classifier: Programming Language :: Python :: 3.5
Classifier: Programming Language :: Python :: 3.6
Classifier: Programming Language :: Python :: 3.7
Classifier: Programming Language :: Python :: 3.8
Classifier: Topic :: Games/Entertainment :: Simulation
Classifier: Topic :: Scientific/Engineering :: Artificial Intelligence
Classifier: Framework :: Robot Framework
License-File: LICENSE.txt
License-File: AUTHORS.txt
